NIB_utils/NIB_utils.py
NIB_utils/__init__.py
example_pkg_nib_utils-0.0.1.dist-info/LICENSE
example_pkg_nib_utils-0.0.1.dist-info/METADATA
example_pkg_nib_utils-0.0.1.dist-info/WHEEL
example_pkg_nib_utils-0.0.1.dist-info/top_level.txt
example_pkg_nib_utils-0.0.1.dist-info/RECORD
