Metadata-Version: 2.1
Name: example-pkg-nib-utils
Version: 0.0.1
Summary: the site package for nib dev team
Home-page: https://github.com/NIB-DEVELOPMENT/NIB_utils.git
Author: NIB-Dev-Team
Author-email: NIB_IT_Dev@nib-bahamas.com
License: UNKNOWN
Project-URL: Bug Tracker, https://github.com/NIB-DEVELOPMENT/NIB_utils.git/issues
Platform: UNKNOWN
Classifier: Programming Language :: Python :: 3
Classifier: License :: OSI Approved :: MIT License
Classifier: Operating System :: OS Independent
Requires-Python: >=3.6
License-File: LICENSE
